{
    "entête": {
        "form": "vers",
        "genre": [
            "chanson",
            "triolet"
        ],
        "subject": null,
        "handwritten_note": false,
        "table_of_content": false,
        "illustration": false,
        "creation": "1652-06-16",
        "change": {
            "@status": "corrected",
            "@when": "2022-05-19",
            "@who": "KA"
        },
        "titre": "Triolets à faire le Tacet sur le temps présent.",
        "dates": {
            "@type": "file_creation",
            "@when": "2021-11-02",
            "#text": "2 novembre 2021"
        },
        "langue": "fra",
        "fichier": "Moreau3846_GBOOKS.xml",
        "langue_detectee": "LGERM"
    },
    "texte": [
        [
            "TRIOLETS",
            "A FAIRE",
            "LE TACET",
            "SVR LE TEMPS",
            "PRESENT.",
            "A PARIS",
            "Chez SIMON LE PORTEUR, au Mont S. Hilaire."
        ],
        [
            "TRIOLETS A FAIRE",
            "le Tacet ſur le temps",
            "preſent.",
            "QVoy! deux Charles nous ont trahis,",
            "Qui ne ſeroit piqué de rage?",
            "Croyant de rauoir leur païs,",
            "Quoy! deux Charles nous ont trahis,",
            "Par là nous ſommes donc appris",
            "Qu’ils n’ont ny force ny courage,",
            "Quoy! deux Charles nous ont trahis",
            "Qui ne ſeroit picqué de rage?",
            "Stuard &le Prince Lorrain,",
            "Que l’on peut nommer gens ſans terre,",
            "Afin de releuer leur train,",
            "Stuard & le Prince Lorrain,",
            "Ont trahy pour le Mazarin,",
            "Et par la paix nous font la guerre,",
            "Stuard & le Prince Lorrain,",
            "Que l’on peut nommer gens ſans terre."
        ],
        [
            "Le fourbe Cardinal de Rez",
            "Qui muguette le Miniſtere.",
            "Croyoit tout prendre dans ſes rez,",
            "Le fourbe Cardinal de Rez,",
            "Il eſt certes plus loin que prés,",
            "D’eſtre ſucceſſeur ou Vicaire,",
            "Le fourbe Cardinal de Rez,",
            "Qui muguette le Miniſtere.",
            "Turenne par vn grand effroy,",
            "S’eſt fort ſenty du mal de ſiege,",
            "Le leua tout en deſarroy,",
            "Turenne par vn grand effroy,",
            "Laiſſans trois mille gens du Roy",
            "Deuant Eſtampes pris au piege,",
            "Turenne par vn grand effroy",
            "S’eſt fort ſenty du mal de ſiege.",
            "Ce Grand Chef decampant en fol",
            "Laiſſa ſon canon dans le ſable,",
            "Et vint camper dedans Treffou,",
            "Ce grand Chef decampant en fol,",
            "Ses trouppes n’ont maille ny ſol,,",
            "La faim & la ſoif les accable,",
            "Ce grand Chef décampant en fol",
            "Laiſſa ſon canon dans le ſable.",
            "Beaufort"
        ],
        [
            "Beaufort ce courage indompté,",
            "A ſeul pourſuiuy la victoire,",
            "Recognoiſſant leur laſcheté,",
            "Beaufort ce courage indompté́,",
            "Eſtant trahy s’eſt degageé,",
            "Retournant tout remply de gloire,",
            "Beaufort ce courage indompté",
            "A ſeul pourſuiuy la victoire.",
            "Duc Charles tu t’ée abuſé",
            "Teé voulant fier à̀ la Reyne,",
            "Iles Mazarins t’ont amuſé.",
            "Duc Charles tu t’és abuſé,",
            "Bien que tu-paſſes’pou ruſé,",
            "Eenſes-tu tenir la Lorraine?",
            "Duc Charles tu t’é́s abuſé",
            "Te voulant fier à la Reyne..",
            "Dans peu Condé́ te fera voir.",
            "Qu’il a le cœur trop bon pour rendre,",
            "Mis au fins de non receuoir",
            "Dins peu- Condé te fera voir,",
            "Ce qu’il tient ne ſe peutr’auoir,",
            "u perdras le temps d’y preten lre,",
            "Dans peu Condé te fera voir",
            "Qu’il a le cur trop bon pour rendre."
        ],
        [
            "Mazarins, Lorrains, Corrinthiens,",
            "Deſtallez hors de nos frontieres,",
            "Ennemis des Pariſiens,",
            "Mazarins, Lorrains, Corintiens,",
            "La France ne vous tient pour ſiens,",
            "On vous talller des croupieres.",
            "Mazarins, Lorrains, Corinthiens,",
            "Deſtallez hors de nos frontieres.",
            "Faiſons vn accord pour iamais,",
            "Du motif fatal de la guere;",
            "Tirons vn lien de la paix,",
            "Faiſons vn accord pour iamais,.",
            "Ioignons nos Armes deſormais,",
            "Pour jetter Mazarin par terre,.",
            "Faiſons vn accotd pour. iamais,",
            "Du motif fatal de la guerre.",
            "Francois, tous d’v -connaccord,",
            "Allons ſuiure nos Alexandres,",
            "Gaſton, Cond́, Conty, Beaufort,",
            "Franç̧ois, tous d’n communaccord;",
            "Allons faire vn puiſſant effort,",
            "Pour mettre Mazarin en cendtres,",
            "Francois, tous d’vn commun accord,",
            "llons ſuiure nos Alexandres,"
        ],
        [
            "A c, gaup il faue mettre à bas,",
            "le Gafanad crdſnl de Baile,",
            "Ceux qui veulent noſtre treſpas,",
            "Ace coup il faut mettre bas,",
            "Faiſons auſſi paſſer le pas",
            "Tout le reſté de la Caballe,",
            "A ce coup il fay mettre, bas,",
            "Le Gallan Cardinal de Biſſe.",
            "A Rome on a renre & pardon",
            "Pour carreſſer des Chappeaux Rouges,",
            "Mettant ſon corps à l’abandon,",
            "A Rome on a rente & pardon;",
            "Mais le Mazarin a le don",
            "D’eſtre entrerenu par ſes gouges,",
            "A Rome on a rente & pardon",
            "Pour carreſſer des Chappeaux Rouges.",
            "Par vn deteſtable atrentat,",
            "Il a desja perdu la France,",
            "Il donne le branſle à l’Eſtat,",
            "Par vn deteſtable artentat,",
            "ll regne comme vn Potentat,",
            "Chacun redoute ſa puiſlance,",
            "Par vn deteſtable attentat,",
            "ll a desja perdu la France."
        ],
        [
            "GrandMonarque, ſongez à vous",
            "On en veut à voſtre Couronne,",
            "Eſloignez ce Chef de filoux,",
            "Grand Monarque ſongez à̀ vous;",
            "Permettez-nous d’eſtre jaloux,",
            "De l’eſtat de voſtre perſonne,,",
            "Grand monarque, ſongez à vous",
            "On en veut à voſtre Couronne.",
            "FIN"
        ]
    ]
}