{
    "entête": {
        "form": "prose",
        "handwritten_note": false,
        "table_of_content": false,
        "illustration": false,
        "creation": "1652-01-28",
        "change": {
            "@status": "corrected",
            "@when": "2022-04-04",
            "@who": "AB"
        },
        "titre": "L'aveuglement du conseil de Sa Majeste, dans les fausses\n          prétentions qu’il a de pouvoir justifier le rétablissement de Mazarin, sur le prétexte de\n          rétablir, par le même moyen, l'autorité souveraine",
        "dates": {
            "@type": "file_creation",
            "@when": "2021-11-02",
            "#text": "2 novembre 2021"
        },
        "langue": "fra",
        "fichier": "Moreau469_GBOOKS.xml",
        "langue_detectee": "LGERM"
    },
    "texte": [
        [
            "L'AVEVGLEMENT",
            "DV",
            "CONSEIL",
            "DE SA",
            "MAIESTE",
            "Dans les fauſſes pretentions qu’il a de pou",
            "uoir iuſtifier le reſtabliſſement de Mazarin",
            "ur le pretexte de reſtablir par ce meſme",
            "moyen l'authorité Souueraine."
        ],
        [
            "3",
            "L’AVEVGLEMENT",
            "DV",
            "CONSEIL",
            "DE SA MAIESTE",
            "Dans les fauſſes pretentions qu’il a",
            "de pouuoir iuſtifier le reſtabliſſe",
            "ment de Maarin; ſur le prerexte",
            "de reſtablir par ce meſme moyen",
            "uthorité Souueraine.",
            "E Cnleils eſt l dene la legne us eonuinnn",
            "peune euele ne le peſeue p e eue.",
            "oir ui Car inni",
            "magine, qu’en diſan; que la diſgrace de ce Miniſtre",
            "etans que l’effet d’vne atentat a l’authorité ſouuerai",
            "lilne rnuienoan deridnoun de nanines on eſl.",
            "eou ir qpen eaeune ie on mne oune e nle",
            "e eemalau deiux aroit nosoleaen eorun les"
        ],
        [
            "moins éclairés voyent bien que c’eſt vn pretexteé, qui",
            "uy ſert de couleur pour en deſguiſer la plus haute in",
            "iuſtice d’Eſtat qu’on ayt amais remarque dans l’hiſtoi",
            "re; & que pout ſe mettre à couuert du blaſme qui luy",
            "en eſt donné par tous les Eſtats de la Monarchie, il ne",
            "trouue point de meieur abry, que celuy qu’il em",
            "prunte de la Maieſté de ſon ſouuerain, dutitre duquel",
            "ne ſe preuaut que parce qu’il s’en eſt heureuſement",
            "empareé contre toutes les couſtumes de cet Eſtar.",
            "Neantmoins, quelque viſible que ſoit ſon aueugle",
            "ment, ie ne l’aiſſcré pas de le mettre dans ſon euidence,",
            "pour faire rougir l’impudence meſme lors qu’elle pre",
            "tendta de le iuifier; & pour leuer la mefiance que les",
            "mples pourroient auoir, de n’eſtre pount dans le plus",
            "iuſte party, lors que ſe l’aiſſant amuſer par cs aparences",
            "trompeuſes, il ſeroient meſme pour croire que le reſta",
            "bliſſemeat de leur tiran ne ſeroit pas iniuſte paree que",
            "niuſtice en ſeroit deguiſee par le pretexte ſpecieux de",
            "raſſeurer le trone contre les ſecouſſes desennemys.",
            "Reſpet bas ne laiſſons point enchaainer nos langues,",
            "& prmy nas ſoufrances reſeruons du hoins la liberté",
            "de nous pl aindre il eſt queſtion de ſçauoit, q’eſt ee que",
            "nous apellons l’authorité Royolſe & la connoiſſance de",
            "ces deux mots, qui nous fet voir ſans obſcurté ou la",
            "uſtice ou l’iniuſtice de ceux qui ſintereſſent auec tant",
            "de vigueur pour le reſtab’iſſemen dC. Maz arin.",
            "A conſiderer l’aut horiteé Royalle, meſme dans le",
            "entimenc de ceux qui l’ont la plus e ſleuée par leut eorm",
            "plaſance: ce n’eſt rien autre choſe qu’vne certaine in",
            "dépendance de pouuoit, qui ne peut point ſouffeir de",
            "contradiétion dans l execion de ſes olonte ſouue",
            "raines; & qui n’eſt pas pluſtoſt eontreqarrée pat les",
            "refiſtancestemeraires de ceuxqui luy ſe ſouſns",
            "qu’elle"
        ],
        [
            "5",
            "qu’elle a le pouuoir de faire proceder contre enx, com",
            "me contre des criminels d’Ettat, qui n’ont que trop teſ",
            "moigné par cée emportement, qu’ils ſont en deſſein",
            "de tout ozer contre le public, puis qu’ils ont eu la hr",
            "dieſſe d’attenter a l’authorité de celuy, qui eſt l’arbire",
            "ouuorain de ſes loix & le dſpenſateur abſolu de rtoure",
            "luſtice.",
            "Voila l’authorité ſuueraine, ce me ſemble auſſi re",
            "hauſée, que ſes plus paſſionnés le pourroit ſouhaiter:",
            "voila ſur vn degré ſi eminent qu’il n’y à plus que le",
            "deſpoique à monter, pour n’eſtre pas moins eſſeuée",
            "que la irannie, ſi toutefois c’eſt eſtre plus releué, que",
            "deſtre monté ſur la teſte, pour eſtre ſoumis à l’indi",
            "gnation des peuples: & de faire trembler ceux qui ſont",
            "dans la dependance, pour eſtre continuellement eſ",
            "branſlé par leurs ſecouſſes.",
            "Mais ſi ce dernier ſe ntiment, quelque aduantageux",
            "qu’il ſoit, fait monter l’authorité ſouuerame iuſqu’à ce",
            "ut degré d’eleuation: on voit bien neantmoins qu’el",
            "len’y monte qu’auec les ſuffrages des peuples, leſquels",
            "renoncant volontairement au droit naturel qu’ils ont",
            "de ne dependre de qui que ce ſoit, en faueur de celuy",
            "qu’ils veulent eſftablir le Iuge ſouuerain de tous leurs",
            "diffet ents: ne marquent que trop que cette indepen.",
            "dancequ’ils luy donnent a eſté dans la dependance de",
            "eurs volontes, & qu’ils ne l’ont mis en eſtat dexiger",
            "eurs reſpects auec authorité qu’à condiuon qu’il ne",
            "eur rauiroit iamais le pouuoir d’en enxiger la iuſtice,",
            "pour le maintien de leur tranquilliteé. Tellement que",
            "celuy qu’ils ont fait le depotaire de cete authorité́",
            "ouueraine, eſt efleué iuſqu’a l’independance de leurs",
            "volonté́s: i demeuare touſiours ſuiet au droit qu’ilsſe",
            "B",
            "?"
        ],
        [
            "6",
            "ont reſerués, de le faire regner en leur rendant iuſtice:",
            "&i’oſe ben aſſeurer en conſequence de cette verite,",
            "que le pouuoir que les penples ont dexiger la iuſtice de",
            "eur ſouuerain, elant anterieur à celuy que le ſouue",
            "rain à̀ d’en exiger du reſpet, puis que celuy cy n’eſt",
            "que le moyen pour arriuer aà cet autre qui eſt ſa fin, les",
            "Monarques ne ſçauroient s’arroger iuſtement le titre de",
            "ouuerains qu’a condon qu’ils ſe ſoumetent volontai",
            "rement à celuy de iuſtes, c’eſt à dire a l’obligatio",
            "ndiſpenſable de ne re gner qu’en rendant iuſtice.",
            "e voudrois ben ſçauoir ſi la Cour, qui fait reſonnet",
            "uec tant d’eſclat cete authorité ſouueraine, en peut",
            "conceuoit des ſenuments qu ſoient plus releuées, tan",
            "dis qu’elle ſe tiendra comme elle dot au deſſous de la",
            "tirannte: c’eſt en ces termes que tous les grands Poli",
            "tiques en ont parlé, c’eſt auec cette condition que tus",
            "es peuples ſi ſont ſoumis: c’eſt en la faiſant va oir ſous",
            "cette illuſtre qualité, que les Charles les h lippes &",
            "es Henrys c’eſt à dire les bien ay mes de leurs peup’es,",
            "en ont fait reſpecter le ioug ſans qu’on ſe ſoit iamais mis",
            "en peine de le ſecouer, parce qu’il n’eſloit impoſé",
            "qu’auec iuſtice.",
            "De cette connoiſſance que ie viens de donner de ’au",
            "thorité ſouuerane, il me ſemble que ie puis fort fa le.",
            "ment paſſer à vne ſeconde, pour fare voir quels ſont",
            "es veritables ennemys quels les veritables partiz ans de",
            "cette meſme authonté, & ce en ſuite de ce taſonne",
            "ment qu’on pourta uſans erteur de la iuſtce on l in",
            "iuſtice das prerentions de la cour, dans le deſſein qu’el",
            "le à de iuſtifier le reſtabliſſement de ſon Mzarin, par",
            "e ptetexte ſpecieux de reparer vne mortelle bre che",
            "qu’on auoit fait a l’authorité Royalle par ſon eſloi"
        ],
        [
            "gnement.",
            "S’il eſt vray, comme il n’en faut point douter que",
            "cette authoriré ſouueraine n’eſt independante de toutes",
            "es volontés de ſes ſuiets, qu’a condition qu’elle ſe rien",
            "dra dans la dependance du deuoir indſpenſable qu’elle",
            "à de leur rendre iuſtice; il n’eſt pas encor moins vray",
            "que cete dependance & eette independance ſont eſ",
            "galement gloricuſes à cette meſme authorité: & qu’el",
            "le doit eſtre auſſi ialouſe de l’honneur qu’elle à d’eſtre",
            "u deſſous de la iuſtice, que du pouuoir qu’elle à de",
            "commander à tous ſes ſuiets ſans eſtre obligée de leur",
            "rendre aucun compte de ſa conduite. Et c’eſt de la que",
            "e pretends conclure auec tous les deſintereſſés: que",
            "uthorité ſouueraine n’a point d’autres ennemys que",
            "ceux qui braſſent des deſſeins au preiudice de cette de",
            "pendance ou de cette independance; cemme’elle ne",
            "reconnoit point d’autres partizans que ceux qui la fauo",
            "riſent dans les iuſtes pretentions qu’elle à d’eſtre inde",
            "pendante de qui que ce ſoit pourueu qu’elle ne s’eſcarte",
            "point du deuoir qui la ſoumet indiſpenſablement à",
            "celuy de rendre iuiſtice à tout le monde. Tellement",
            "que ceux qui cnſeillent à leurs ſouuerains de ne gou",
            "uerner leurs ſuiers que par leurs caprices, n’attentelt",
            "pas moins criminellement à leur authorité, que ceux",
            "qu pratiquent ſecretement les eſprits des Peuples pour",
            "eur faire ſecoüer leur ioug: parce que, cette ndepen",
            "dance des voſontés des Peuples n’eſtant qu’vne con",
            "dition neceſſaire, pour pouuoir maintenir l ur traquil",
            "lité en leur rendant iuſtice, il ſenſuit neceſſairement,",
            "que des que le ſouuerain ſe diſpenſe de rendre iuſtice",
            "en ſe gouuernant par ſes caprices, il diſpente ſes ſuis",
            "de l’obligaon qu’ils u’auoient à luy obeyr, qu’a con"
        ],
        [
            "dition qu’il ne ſe diſpenſat point luy meſme de ceſls",
            "de leur rendre iuſtice.",
            "Ce raiſonnement ne ſouffre point de replique, que",
            "de la bouche des Tirans; & ie ne doute point que la",
            "Cour de France qui n’a iamais affecté qu’vn gouuerne",
            "ment de douceur, n’y donne les mains pour le forti",
            "fier encor par ſon aurhorite. C’eſt neantmoins cette",
            "vetité que ie pretends faire ſeruir de fondement à la",
            "uſtice ou à l’iniuſtice des pretentions qu’elle à, de",
            "tifier le reſtablſſement de ſon Mazarin. par le pre",
            "txte de reſtablir l’authorité ſouueraine n otablement",
            "eſcheüe, comme elle pretend, par l’ſloignement de",
            "pieunue e reue elee i e e’ſeree",
            "ce Miniſtre. Et pour cet effet il eſt queſtion de ſçauoir",
            "Royalle, ſi l’eſloignement du C. Mazarin, fut vn",
            "trtentat à cetre meſme authorité.",
            "Pour monſtrer que l’eſloignement do C. Mazarin",
            "fut vn attentat a l’authorité ſouueraine, il faudroit",
            "faire voir que ceux, qui l’ont procuré, ont attenté au",
            "ue ne le en e e nui eronenoe ne uenuoneie",
            "volontés deſes ſuiets, pendant qu’elle eſtoir la plus at",
            "tachée à l’obligation de leur rendre iuſtice: parce",
            "que ſi l’on peut faire voir Jqu’il eſtoit de la Iuſtice du",
            "Roy deſlogner cex inſolent Miniſtre, o prouue tep",
            "manifeſtement que ceux qui oat obligé ſa Majeſté à",
            "cet eſloignement, bien loing d’atenter à ſon autho",
            "rité, ont pluſtoſt monſtré qu’ils en eſtoient les ve",
            "rirbles zelateurs; & que ceux qui le reſtabiſſent,",
            "en ſont par meſme couſequence les verirables en",
            "nemys"
        ],
        [
            "9",
            "n’eſtoit pas moins de la iuſtice du Roy, d’éloigner",
            "e Cardinal Mazain, que d’aſſouuir les ſouhaits ge",
            "neraux de toute la Monarchie, qui ne conſideroir cé;",
            "nſolent Miniſtre que comme le tyran de ſa liberté, &",
            "ſanue vniuerleile de tue la plus pure lubſtance",
            "de ſes ſujets, Ceue haine de out l’Eſtat, qui poſſe.",
            "doit é́galement les elpnis, & des méchans & des gens",
            "de bien eſtoit ſi generale, que le Roy ne pouuoit point",
            "s’cpiniaſtrer au deſſein d’en proteger l’objet, à moins",
            "que de renoncer à l’obligation que ſa Maieſté auoit de",
            "gonuerner ſes ſubiets auec luſtice, c’eſt à dire de les",
            "ffranchir du gouuernement de celuy qui leur eſtoit",
            "nſupportable: & qui pour cette ſeule raiſon meſme",
            "qu’il n’eſtoit pas au gré́ des peuples, deuoit eſtre eſloi",
            "gné du maniment des affaires, quand bien il s’y fſt",
            "d’ailleurs comporté auec toute la moderation qu’on",
            "ç̧auroit exiger d’vn parfait Miniſtre d’Eſtat...",
            "e ſcay bien que la aine que certains particuliers",
            "peuuent conceuois contre yn Miniſtre d’Eſtat peudant",
            "qu’il eſt dans l’approbation generale de tout le refte",
            "des ſubjets ne dot paſſer que conmme vn caprice, o",
            "comme vn reſſentiment iniuſte de quelque mauuais",
            "traitemsent pretendu; que le Souuerainne doit couſi",
            "derer à tout rompre, qu’ defſein d’y ponmoir pa",
            "quelque acomnmodement politique, fi outefois il he",
            "pas a ſez rigoureux pour les ranget. à det deuoit par",
            "es voyes de laſeueriré: Mais lors que l’indignationes:",
            "generale; & qu’il n’y a que certains particuliers que",
            "e aotif honreax de l’intereſt autache encore à ſouſte.",
            "nir l’a horité dce mauuais Miniftro, l ne fqut poins",
            "douter, que le Roy qui le prontege. s’oublre du pna",
            "mier de tous fes deuoirs qui eſt de rndne iuſtié ài fap"
        ],
        [
            "3",
            "uits, dont il e ſe peut point qe le ḿ contentement",
            "oit general, ſans raſon, & contre lecuel il ne peut",
            "point pretendre que ſa ſatis faction particuliere doit",
            "preualoir, parce que ce ſeroit regner en tyran contre",
            "es maximes de la veritable Royauté, qu condam",
            "ment touſiours les caprices des ôonarques, lots qu’ils",
            "e portent, pour complaire à quelquvne de leurs tan",
            "taiſies, à choquer les inclnations generales de tous",
            "eurs ſuijets; dont le contentement gene al doit ſans",
            "doute eſtre preferc aà̀ leur particulier, pus qu’ils ne ſe",
            "ont ſoumis à reconnoiſtre leur pouuoir, qu’a condi",
            "tion, qu’ils ne s’eu ſeruiroent pas, pour en opprmr",
            "eur liberré, ce qu’ils feroient ſans doute, ſi pour ſe",
            "complaire,ils vouloieut déplaire à tout le monde.",
            "Ie parle bion ltbrement, mais c’eſt auec grand reſ",
            "pect, ſi l’on veut iuger de mon raiſonncment ſans paſ",
            "fſion. Il reſte maintenant à faire voir, ſi cette haine de",
            "toute la France contre le C. Mazarin eſtoit aſſez ge",
            "nerale, pour ohliger la iuſtice du Roy, au deſſen d’en",
            "éloignerl’obiet, quelque inclination particuliere qu’il",
            "euſt à ſe proteager C’eſt à quoy ie penle que i puis",
            "pleinement ſatisfaire, en diſant qu’il eſtoit inſuppor",
            "table au Clergé, que la Nobleſte ne reſpectoit ſes or",
            "dres qu’auec honte, que le Tiers eſtat n’attendoit plus",
            "que l’occaſion de ſe ſouſleuer, pour en dépeſcher le",
            "onde: que Son Alteſſe Royale, c’eſt à dire le Lieu",
            "tenant General de l’Eſtat ne le pouuoit plus ſouffrir,",
            "quetous les Parlemens de France fulminoient tous les",
            "ours contre ſa conduite; que les Genetaux des ar",
            "nmées ſe plaignoient hautement du manquemeut de",
            "fioances, pour la deffence de nos conqueſtes, pendanr",
            "que le Mazarin employoit des millions à des ſimples"
        ],
        [
            "decorations de Theatre: Etpourt dite en vn mot, que",
            "e Cardiual n’eſtoit approuué dans l’Eſtat, que de ceux",
            "qui eſtoient obligez de s’intereſſer pour ſa conſerua",
            "uon, par laſeule neceſſité deſe maintenir dans le re",
            "hauſſement de leurs forunes. Cette verité eſt ſi eui",
            "dente, que les Maarins meſme ſont obligez de con",
            "feſſer que leur maiſtre eſtoit generalement, comme il",
            "eſt encor hay de tout le monde: Et ſi le Roy, c’eſt à",
            "dire ſon Conſeil ou ceux qu s’y ſont ingerez, s’imag",
            "ne encore que malgré cette hane generale de tout",
            "Eſtat, ſon authorite ſe trouuoit engagée aà ſouſtenit",
            "e Mazarin; il prerend donc que ſon contentement",
            "particulier doit preualoir par deſſus le general; qu’il",
            "mporte fort peu que tous ſes ſuiets gemiſſent. pou",
            "ueu que ſa Maieſté ſoiz dans vne parfaite poſſeſſion de",
            "tous ſes plaiſirs, nmeſme les plus indiffer ens; & que le",
            "capricede celuy qui n’eſt aſſis ſur le Thtoſne que pour",
            "exercer la iuſtice, ſoit plus conſideré́ que le contente",
            "ent general de tous ceux qui ne ſe ſont ſoumis à le",
            "reconnoiſtre, qu ’à condtion qu’il ménageroit leurs",
            "tereſts auec aotant de douceur que deiuſtice.",
            "Ces maximes eſtoient autrefois teçeuës dans la",
            "Cour de Neron;, comme ie ne doute point auſſi qu’el",
            "les ne ſoient auiourd’huy bien pratqueées dan celle",
            "du granl Seigneur: Mais la Cour de France a de tout",
            "temps affecté vn Empire plus humain; Et les helles",
            "parolles dont nos Roys ont accouſtnmé de le ſeruir",
            "dans toures leurs Declatations pour exprmer leut",
            "fection paternelle enuers leurs pepis ; ne mar",
            "quen que trop, que bien loing de vouloir, q’n de",
            "eurs caprices preuaille par deſſus le eontentement",
            "general de tous leuts ſubiets; ils ont pluſtoſt eux meſ"
        ],
        [
            "ra",
            "mes aſſez de bonté pour ſe priuer de leur repos parti",
            "ticulier afin de le procurer à tout le monde: Et cette",
            "conſideration a eſt́ pluſieurs fois ſi puiſſante dans l’eſ",
            "prit des Eſtrangers, que les peuples entiers ſe ſont de",
            "membtez de l’ancien domaine de leuts Courones na",
            "tutelles, pour venr gouſtor ſous la noſtre, la douceur",
            "d’vn Empire plus raiſonnable; & voir enfin reſpirer.",
            "eur liberté ſous le commandement des Lys.",
            "Ce raiſonne ment faie voir que ceux qui preſſerent",
            "nńe paſſeée l’eſl oignement du C. Mazarin, bien",
            "oing d’attenter à l’anuthorité Souueraine, donnerent",
            "pluſtot de treuiſſantes preuues de la paſſion qu’ils",
            "auoient de la maintenir; & de ne permettre pas qu’el",
            "le ſouffrit aucun notable é́chec, pendant que tous les",
            "Eſtats de la Monarcte, ſembloient exiger de ſa iuſti",
            "ce qu’elle ne s’attachaſt point iſqu’à la protection de",
            "celuy, dont le ioug tyrannique leur eſtole iuſtement",
            "nſupportable. On pourroit encore adiouſter à ce rai",
            "ſonnement pour vn ſurcroiſt d’euidence, qu’vne ſeu",
            "le Regente le ſuportant malgré les ſentimens de tout",
            "on Conſeil, & l’auerſion generale de tous les peuples,",
            "on auoit encore d’autant plus de ſuiet de le pouſſer à",
            "out, que moins il auoit raiſon de ſe preualoir de la fa",
            "ueur d’vne Minorité. Mais le precedent ſeul eſt inuin",
            "cible, s’il ne trouue que des raiſonsables pour er",
            "ger.",
            "Cela eſtant preſuppoſé ilne me reſte rien qu’à con",
            "clurre contre l’iniuſtice des pretenſions de la Cour,",
            "ou du Conſeil de ſa aeſté, qui en eſt venu iuſqu’à ce",
            "point d’aueuglement, que les reſtabliſſeimens du Ma",
            "ann & de l’authorité Royalle ſont inſeparables; &",
            "qu’il n’eſt pas poſſible que cette derniere ſe remette",
            "dans."
        ],
        [
            "13",
            "dans ſa premiere ſplendeur, à moins que le premier",
            "ne remonte dans lon premiet éclat: Aueuglement ſi",
            "pitoyable, qu’il n’eſt pas moindie, s’il ne paſſe au de",
            "là d’vne inſenſibilité pohtique; & qui plus eſt, en ſui",
            "te duquel nous pouuons dire. que les intelligences de",
            "cét Eſtat ſont moins intelle ctuelles que capricieuſes,",
            "puis que les iniuſtices meſmes qui chequent le ſens",
            "commun, ne paſſent point dans leurs ſentimens de",
            "prauez que cohme des parfaits coups d’Eſiar.",
            "Ceſt reſtablir, diſenls l’authorié Souueraine,",
            "que de reſtablir le C. Mazarin. C’eſt à dite c’eſt re.",
            "ſtablir l’authoité́ Souueraine, que de r mettre dans",
            "ntendance de ſa condte, celny qui ne s’eſt iam ais",
            "ruy de lon pouuoir que pout en faire valoir les inte",
            "reſts de ſa Maiſon, au preiudice de ceux de l’Eſtat.",
            "C’eſt reſtablit l’Authorté Souueraine, que de redon",
            "ner la protection Roy alle vn Tyran, qui s’eſt en.",
            "graiſſe de toute la plus pureſubſtance de cet Eſtauc’et",
            "ret ablir l’uthorité Souueraine, que de faire gouner!",
            "ner les peuples, par le Miniſtere de celuy qui ’eſt la",
            "cauſe genepalede routes les calamit éz publiques :c’eſt",
            "reſtabſir l’Autdirité Souuerainé, que de fate remon",
            "er uprez duitinon de cét Eſtar, celuy qu’oen pre",
            "cipité, u’apres les corinoiſſances qu’on en a eu, qu’il",
            "faiſoitéchoûenoſtre fortune ou par imprudence ou",
            "par’malice, à toute ſorte d’écueils: ceſt reſtablitl’Au.",
            "thorité Souuerame que de choquer tous les Prindesde",
            "Eftat pour éônplaire à vn eſtrange:’c’eſtreſtabiir",
            "Authorit Soueraine que de donner occaſio à vn",
            "rmemient genérſl, qui ſera peuiſtre pour la deſtrui.",
            "re ſi quelqu Prouidence plus particuliere y net la",
            "uainC’at reſtablit l’uthorié Souueraine que d’1s",
            "D",
            "L"
        ],
        [
            "14",
            "ter tous les peuples reoltez, par la preſence de ce.",
            "uy qu’ils ne ſoutfiront iamais que lors qu’auec toute",
            "orte de violences ils ne pourront point en ſecoü̈er le",
            "oug c’eſt reſtablir l’Authiorité S ouueraine, qued’en",
            "ha2zarder la decadance par le reſtabliſſement de ce",
            "luy qui portera toute la haine & toute l’indignatlon",
            "des peuples dans le patty de ſa Maieſté́: c’eſt dſſenls",
            "reſtablir l Au orité́ Souueraine, que de vouloir ſou",
            "ſtenir la cheute d’vn mauuais, Miniſtre, que S. A. R.",
            "qe Meſſieurs les Pcinces, que les Parlemens, que les",
            "domeſtques que les Eſtrangers meſmes, & que tou",
            "les Peuples de l’Eſtat, ne ſoufftiront iamais dans le",
            "niment des affaires de cette Monarchie.",
            "Que vous en ſemble Meſſieurs les Politiques ’eſlL",
            "de moyen plus aſſeurez pour ruiner l’authorité Souue.",
            "raine, que celuy dont le Conſeil de ſa Maieſté ſe ſert",
            "pour la reſtablir? peut on attaquer plus direétement",
            "cette aurhorité, qu’en luy copleillant la protection de;",
            "celuy contre lequel on eſt ſur le point defaire vne",
            "croiſade, comme ſi c’eſtoit encor vuennemy da la Re.;",
            "gion? pour faire ſubſiſter cette authoriré Royale,,",
            "eſl de plus ſolide fondement que l’aour des peu",
            "ples, que cette prorection n’offence pas moins mor.",
            "tellement, que ſi ſa Maieſté declaroit ouuerement,",
            "on deſſein pout l’exer cice d’vne prochaine tyranie!",
            "falloir du moins qu’vne complaiſance de quelque",
            "temps donnaſt loiſir à la fureur des peuples de raſſeoir;,",
            "& qu’on eut aſſez de raiſon pour croire que le baniſſe",
            "ment de cet inſolent Miniſtre. n’eſtoit point ſupoſé,",
            "fin quetant qu’on ne ſe duteroit point deſon retour,",
            "on peutſe preualoir de l’ocçaſion de le remetge, pen",
            "dantque les reſiſtances n’en ſerot point dangereuſes",
            "...",
            "4"
        ],
        [
            "14",
            "Mais de lerapeller au milieu d: l’armemient gener;",
            "qu’on faiſoit poar la ſeulle aprehe ſi de ſon retour",
            "de le reſtablir pendant que tout l’Eſtat eſt ébranlé",
            "pou le perdre; de le proteger pendant que tous les",
            "peuples crient au voleur, autyran, au fouthe, au pet",
            "turbateur du repos public, de le vouloir ſouſtenir pen",
            "dant que les reuoltes generalles qu’on fait pour cet",
            "effet, ébran’ent tout l’Eſtat: n’eſe pas choquer auſ",
            "ſi directement l’authorité Royale, que ſi l on appli",
            "quoit ſecrctement les mineurs aux fondemens de ſon",
            "hroſne pour le faire tomber ſans teſource. Tout ce",
            "diſcours eſt à l’eſpreuue.",
            "FIN."
        ]
    ]
}