{
    "entête": {
        "form": "prose",
        "handwritten_note": false,
        "table_of_content": false,
        "illustration": false,
        "change": {
            "@status": "corrected",
            "@when": "2022-10-25",
            "@who": "AB"
        },
        "titre": "La véritable union des princes et des peuples pour la\n          cause commune.",
        "dates": {
            "@type": "file_creation",
            "@when": "2022-10-25",
            "#text": "25 octobre 2022"
        },
        "langue": "fra",
        "fichier": "Moreau3967_GBOOKS.xml",
        "path": "Corpus\\Mazarinades\\3901-4000\\Moreau3967_GBOOKS.xml",
        "json_path": "Corpus\\Mazarinades_jsons\\3901-4000\\Moreau3967_GBOOKS.json",
        "langue_detectee": "LGERM",
        "lexicalites": [
            0.7857142857142857,
            0.7016574585635359,
            0.7325102880658436,
            0.7649253731343284,
            0.707635009310987,
            0.7137546468401487,
            0.7407407407407407,
            0.7551020408163265
        ],
        "lexicalite": 0.7270554493307839,
        "ecarts": [
            -0.0840568271507498,
            0.03085282950230772,
            0.032415085068484784,
            -0.057290363823341406,
            0.00611963752916167,
            0.026986093900592034,
            0.014361300075585781
        ],
        "ecart": 0.0360117338643176
    },
    "texte": [
        [
            "LA VERITABLE",
            "VNION",
            "T",
            "DES",
            "PRINCES",
            "ET DES PEVPLES,",
            "pour la cauſe commune.",
            "PARs.",
            "a e ne pnſe en",
            "nnne, pone le palai",
            "sen"
        ],
        [
            "21",
            ":",
            "e",
            "a x",
            "t Dr a",
            "u rR1",
            "LA VERIT’ABLE VNION",
            "des Pninces, & des Peuples",
            "7r Dsjir la",
            "1 ſ r",
            "pour la cauſe commune.",
            "A R noſtre Diſcours Imprimeé depuis pen,",
            "JJ Intitulé, lnftruffions Politiques, preſenitées-",
            ". Noſſeigneurs de la Cou de Parlemoomt,;",
            "Noas auons fait voir comme lalconnoiſſfan",
            "ce de la Politique & de ſon vſage eſt heteſ.",
            "laire, ſoit à ceux qui-poſſedent, ou aſpirent auxi em",
            "plois publies de qu’elle nature qu’ils ſoient, pour s’en",
            "acquittor auec la prudence requiſe & neceſſair, &",
            "paſſerauec gloire dans les oſſemblées & de liberations",
            "Publiques & Politiques, auſquelles leuss chargés les",
            "appellent, ſoit aux particulieres, tant pour leur vſage",
            "particulier pour lire les Hiſtoires vtilement, & auce",
            "ontentement d’eſprit, paroiſtre auec honneut das",
            "es Compagaies & conuerſations partioulleres ſur les",
            "entretiens & raiſonuemens des Hſtoires, & des nou",
            "uielles & affaires du emps, & ſe conduire & demeſles",
            "auec àdreſſe & prudence. dansles: affaires du monde,",
            "meſme partitulieres, à auſe de la correſpondanee",
            "qu’elles ont leplusſouuent auec les affairespubliquev,"
        ],
        [
            "4",
            "qu’aſi pous la traaquillité publiqnse, pour aquieſeer",
            "auecmoinis de repugaance aux Edicts & Ordonnan",
            "ces des Souuerins, encônnoiſſans les raiſons & l’vri",
            "liré publique, par la connoiſſance que la ſcience de l",
            "Poliique en ſuggeres Et ce au moyen de l’explieal",
            "tion, & deſduise eu general ce que nous y auons faite",
            "du fondement & connexité de chacune des matieres",
            "d’icellespar des raiſons & authoritez curieuſes &re.",
            "marquables; en ſorte que ceux qui prendront la pei",
            "pe de les lire entirtment, pourront qu’y proſi",
            "ter beaucoup, ieſmes acquerir vne connoiſſance ge",
            "nerale de tautesles matieres de la Polirique, pour s’en",
            "erie vtilement & auee aduantage dans ous les cas",
            "& rencoatres remarquez cy-deſſus:, Mais la neceſſité",
            "importance de cetteſeine & de ſon vſage, paroi",
            "ſtea encore nieux par la neceſſitcé & imporeance de ſa",
            "fi & de ſo ſujet, qui eſt la conferuation de la Re",
            "publique, par la conſeruatio de l’vnion des peuples",
            "&des Princes entreux.",
            "Or pour cela il eſt neceſſaire de rematquer que l’v",
            "nion & ſocieté qui doit eſtre entre les hommes, eſt de",
            "elle neceſſité pour leut comrmune ſubſiſtance, qu’elle",
            "et àbon droitappelleée l’ame du monde, & vne har",
            "moaie; car comme le corps ne peut ſubſiſter ſansſon",
            "Ame, ny l’harmonie apres la deſvnion des ſons, ou le",
            "compoſé apres la diſſolution des Elements. Ainſi les",
            "hommes ne ſçauroiear ſubſiſter ſans cette vnior, con",
            "orde & ſocieté mutuelle, d’autant qu’ils defaillent",
            "en eux"
        ],
        [
            "1",
            "eeux-meſmes de beaucoup de choſes abſoluëment ne",
            "ceſſaires pour l’entretien & ſubſiſtance de leur vie, leſ.",
            "quelles ils ne peuuent auoir qu’en autruy, & en la ſocieté́",
            "& communion de pluſieurs: Dieu ayant deſnué́ à deſ",
            "ſein l’homme de toutes ces choſes, afin qu’il fuſt obligé",
            "pat ſa propre neceſſité de les rechercher en autruy, &",
            "pour cét effet conſeruer l’vnion & ſocieté́ auec ceux de",
            "qui il les pouuoit retirer; Tellement qu’vn ſeul ne",
            "pouuant eſtre Vigneron, Laboureur, Cordonnier,",
            "& de toutautre meſtier, & neantmoins chaqu’vn ayant",
            "beſoin de toutes ces choſes, & d’ailleurs ne pouuan",
            "ſeul ſe defendre contre les iniures & attaques de leurs.",
            "ennemis, ils furent contraints de faire vne Congrega",
            "tion & Societé de pluſieurs, en laquelle tous contri",
            "buans de leur trauail, de leur eſprit, & de leur induſtie,",
            "ſelon leur portée, vn chacun trouuat en autruy, & tous",
            "entous ce qui leur eſtoit neceſſaire pour l’vſage de la vie:",
            "VMoire meſne afin que les principaux membres de cetre",
            "Congregation ne vinſlent ̀ donnet lieuà la deſvnon",
            "& diſſolution de cette concorde ſi neceſſaire pour la",
            "ſubſiſtance de tout le coips par le mépris des moiudres",
            "parties; Dieua fait que celles qui ſemblent les plus vil",
            "les & les plus abiectes y ſont les plus neceſſaires à̀ la",
            "rie, comme les Laboureurs. De là ſe ſont formez les",
            "Corps & Communautez des Bourgs & Villes, meſmes",
            "anciennement les ſeules familles ompoſoient des vil",
            "les, & des Republiques, ce qui ne doit pas ſeémbler",
            "eſtrange, d’autant que nos premiers parens viuoient",
            "ort long temps, & eſtoient grandement feconds, ayans"
        ],
        [
            "pluſiouys fetmimes & concubines, tellement que pen",
            "dant leur vie, ils auoient pluſieurs enfans, perits fils,",
            "riere fils, & autres deſendans, leſquels comme ils",
            "eſtoient en grand nombre, ils compoſoint comme",
            "vne eſpece de Republique: Voire meſme ces familles",
            "comprenoient en elles la ſemence de toutes les eſpeees",
            "de domination, ainſi que remarque Ariſtote dansſa Po.",
            "ltique, lors qu’il déduit de l’eſtat des familles, les di",
            "uerles eſpeces de Republique.",
            "Apres comme par l’augmentation des familles v",
            "ſeul lieu ne les pouuoit pas contenir, ils furent contrains",
            "de ſe diuiler en diuers corps, & diſtinguer leurs poſſeſ",
            "ſions, & ainſi les Piovinces, Empires & Royaumes ſe",
            "ſont eſtablisde degré en degre: Ce qui fait dire à Sains",
            "Auguſtin dans la Citeé de Dieu, Que le monde eſtoit",
            "vne Republique qui comprenoit tous leshommes, qui",
            "auoit pour Prince & Seigneur la raiſon, dont l’Empire a",
            "autant d’eſtenduë que le monde: Surquoy l eſt remar",
            "quable qu’afin que ces peuples ainſi diuiſez, fuſſen",
            "pourtant obligez d’entretenir & conſeruer cette vuion,",
            "non ſeulement par la neceſſité de defenſe contre leurs",
            "ennemis, mais auſſi par la neceſſité de la vie & du com",
            "merce, Dieu a fait qu’vne meſme terre ne pdrte pas tou",
            "te ſorte de fruicts, afin que les Habitans de la Region",
            "qui n’a pas du blé, du vin, des huiles, ou des laines par",
            "exemple, ſoient obligez de les tirer des habitans decelle",
            "qui en a, & pour cets effet conſeuer & maiatenir auec",
            "eux cette vnion & ſocieté: En ſorte que l’vnion& cor",
            "reſpondance de ces corps eſt de telle ne ceſſité & conſe <pb",
            "n=\"7\"/>",
            ". 2",
            "quence por la ſabſiſtace meſme des particuſiers quiles",
            "conapoſent, que leur diuiſion & diſſolution enttaiſne",
            "neceſſairement la deſtruction du tout, & des parties, ne",
            "plus ne maoins que la diſſolution de l’vniondes Elemens",
            "celle du conmpoſé, & en eſftet, nous ne voyons rien qui",
            "eauſe plusoſt a ruyne des familles, das Villes, & des.",
            "Eſtats, que la diſcorde..",
            "Caaond res para creſnt, diſcondins vera:",
            ". iediabuns.;.!",
            "La neceſſiteé de cette vhion& contotdes our le bien &e",
            "ytilité́ commune de tout le corps, s le deuoit de toué",
            "les membres qui le compoſent, ſe pet encore mieu",
            "éclaircirpar la meſfme comparaiſon u corps humain;",
            "& de ſes membres, de laquelle ſe ſeruit jadis vn Ci.",
            "toyen Romain, pour reconcilier & reüiair le peple de",
            "Rome auec le Senat, lors que le menu peuple ſe fut",
            "recire au Mont Auentia pour s’oppoſer à l’auharité que",
            "le Senat youloit vfurper ſur luy, ainſi que rappore Tire",
            "Liue dans l’Hiſtoire Ronmaine.- Car le corps hai",
            "eſt ecompoſé de parties & membres differents, chaqu’va",
            "deſquels contriboaë par vne mutuelle concorde. & har",
            "nonte à l’entretien & vtilité des autres parties, &da",
            "tout qu’elles eompoſent vne cliaqu’vne ſeloo les quuali",
            "tex & fontions differentes qu’elle en a reeeaude la Na",
            "ture: Ainſi la main a ſa fonction dfferentede celle du",
            "ied, l’œil de cel le de l’oreille, la bouche de colle de l’e",
            "omach, la raiſon de celle desſens, & ainfi. des autêe",
            "partuies & facultez du corps, & noanrmois elles oot",
            "toutes va meſme bat, quieſt l’entretien& canſeuaidn"
        ],
        [
            "8",
            "de tout le eorps, & d’elles-meſmesen iceluy, cela eſtans",
            "remarquable, quebien que chaqu’vne de ſes parties ſem",
            "ble n’agirt que pour l’vtlité d’autruy, la main ne pre",
            "nant pas pour ſoy, l œil ne voyant pas pour ſoy, &c.",
            "Neantmons c’eſt principalement pour la leur propre,",
            "leur intereſt & ſubſſtance particuſiere eſtant tellement",
            "liée auec celle des autres parties, & de tout le corps, que",
            "l’vne ne peut ſubhſter ſans l’autre: Et en effee, ſi la",
            "main, les pieds, la bouche, l’œil & les autres parties du",
            "corpsotules principales d’entr’e lles ſeulement viennens",
            "à ceſſei de fatre leurs fonctions naturelles & ordinaires,",
            "& abandoner e ventre, ſouz pretexte qu’il reç̧oit &",
            "renferme le fruit de toures leuts peines, incontinent",
            "on les vetta ſecher, & perir elles-meſmes auec iceluy:",
            "Ainſi les familles, les Villes & les Eſtats ſont compo",
            "ſez de perſonnes & membres dfferents doüez de quali",
            "rez, fontions & meſtiers tous diuers, leſquels chaqu’vn",
            "eſt obligé de faire valoir & exercer pour l’intereſt de ſa",
            "propre ſubſiſtance au moyen du commerce, & pour le",
            "bien commun de tout le corps, l’vn ne pouuant ſe paſ",
            "fer des fonctinas & de l’aide de l’antre, en ſorte que i",
            "ees partes viennent à rompre leur commerce & vnion",
            "mutuelle des vnes auec les autres, elles ne peuuent que",
            "perir elles-meſmes auee tout lecorps, ne pouuaus ſub",
            "filer l’vne ſans l’autre.",
            "Cela poſé, il eſt-aiſé de comprendre que cette vnion",
            "&e conorde eſtant ſi neceſſaire pour la ſubſiſtance &",
            "conſeruation de tout le corps en general, & de chaqu’vn",
            "desmemhres d’iceluy en particulier, il faut neceſſaire",
            "ment,"
        ],
        [
            "93",
            "que, comme dans lIe corps humain Dieu a mis laraiſon",
            "& les regles d’icelle pour la conduite des fonctions de",
            "toutes les parties & membres d’iceluy au bien & vtilité",
            "ommoune du tout, & de ſes parties: qu’ainſi dans les",
            "corps des familles, des Villes, & des Eſtats, il y ait vn",
            "ordre des regles & des chefs pour regir & conduire les",
            "ations & deſſeins des partieuliers au bien & aduantagé.",
            "publie de tout le corps: Et qu’à iceux à cet effet les par",
            "ticuliers ſoient aſſujettis, & demeurent vnis pour leur",
            "vtilité commune, comme les membres du corps le ſont",
            "à la raiſon, & ce quand meſme l’intereſt particulier d’i",
            "ceux ſembleroit s’y oppoſer, & en receuoir dupreiudi",
            "ce, dantan que les particuliers ne doiuent pas ſeule",
            "ment auoir ſoin de leur vrilité́, mais auſſi de celle de la",
            "Communauté, l’intereſt de laquelle eſt dautant plus con:",
            "ſiderable quela ſocieté eſt grande: Or étordre, & ces",
            "regles ſont preſcrites & contenuës dans la ſeule ſcien",
            "ce & vſage de la Politique, & ceux à qui l’execution en",
            "eſt eommiſe, ſone lea Roys & Prinees & les Magiſtratse",
            "Et ainſt il eſt certain qu’autant noble, excellente & ne",
            "ceſſaire qu’eſt cette vmon, ſocieté & concorde mutuel",
            "le, quifait tout le bon-heur, & toute la ſubſiſtance des",
            "famlles, des Villes, & des Eſtats & Republques, au",
            "tant eſt noble, importante & neceſſaire la connoiſſance",
            "de la Politique, puis qu’elle enſeigne l’art & les moyens",
            "de les bien eſtablir, conſeruer & regir, & ainli autant:",
            "releuée par deſſus les autres ſciences, que la iaiſon par",
            "deſſus es membres du corps humain, & l’eſtat & lin",
            "tereſt publiec par deſſus le patieulier: Et autant qu’eſt",
            "aeceſſaire la raiſon dans le corps humain, pour la con",
            "3"
        ],
        [
            "10",
            "duitte des actions des membres d’iceluy, au bien de tout",
            "le corps, autant ſont neceſſaires les Princes &. Magi",
            "ſtrats dans les Eſtats pour la dretion des actions des",
            "parti uiers, au bien & repos de tout le corps: Ainſi",
            "donc comme les actons des Chefs, Ptrinces & Magi",
            "ſtrats doiuent tendre à la conſeruation de cette vnion &",
            "ſoceté au bien & repos detout l’Eſtat, ainſi les Subiets",
            "ence cas leur doiuent toute ſoumſſion & obeyſſance,",
            "ſans que pourcela les Princes & les Peuples ſe puiſſent",
            "eſtimer moins hbres, ainſi qu’il pourra eſtre particulie",
            "rement monſté par vn autre diſcours, intitulé, La vari",
            ". tble liberté des Princes & des Subjets.",
            "De ce que deſſuson peut recuellir combien ſe trom",
            "pent ceux qui s’imaginent que les regles & preceptes",
            "de la Politique ne ſeruent qu’à regir & conduire les",
            "Roy aumes & mpes, ne conſiderans pas que les corps",
            "des familles, notamment des grandes maiſons, ſont des",
            "petits Eſtats, les affaires deſquelles par conſequent ont",
            "la pluſpart du temps beaucoup de c orreſpondance auec",
            "les affures Publiques des Royaunes & Repubiiques, qui",
            "à’ vray dire, ſont les familles des Roys & Princes, meſme",
            "les familles particulieres contienaent en elles les ſemen",
            "ces de toutes les eſpeces de domination, ainſi que re",
            "mr que Ariſtote dans ſa Politique, diſant que l’authori",
            "té des Peres ſur les enfans, reprelente l’Eſtat Monarchi",
            "que; l’authorité du mary ſur ſa femme; l’eſtat Ariſtocra",
            "tuique; & l’authorité du fils aiſné lur ſes freres l’eſtat de",
            "mcratique: Er en effet l’œconomie qui traitte du ſoin",
            "partieuler de la famille d’auee les autres Eſtats, n’eſt",
            "qu’vne partie de la Politique parmy tous les Philoſo"
        ]
    ]
}