{
    "entête": {
        "form": "prose",
        "genre": [
            "arrêt",
            "texte officiel"
        ],
        "handwritten_note": false,
        "table_of_content": false,
        "illustration": false,
        "subject": [
            "Aliments – Approvisionnement – Paris (France)",
            "Paris (France)"
        ],
        "change": {
            "@status": "corrected",
            "@when": "2022-03-09",
            "@who": "AB"
        },
        "titre": "Arrêt de la cour de parlement de Bordeaux, portant\n          injonction à tous les marchands du haut pays de faire descendre, par la Garonne, des bleds\n          sur le port et havre de la présente ville, pour subvenir à la nécessité de Paris.",
        "dates": {
            "@type": "file_creation",
            "@when": "2022-03-02",
            "#text": "2 mars 2022"
        },
        "langue": "fra",
        "fichier": "Moreau168_MAZ.xml",
        "path": "Corpus\\Mazarinades\\101-200\\Moreau168_MAZ.xml",
        "json_path": "Corpus\\Mazarinades_jsons\\101-200\\Moreau168_MAZ.json",
        "langue_detectee": "LGERM",
        "lexicalites": [
            0.7792207792207793,
            0.75,
            0.7272727272727273,
            0.7486338797814208,
            0.6851851851851852
        ],
        "lexicalite": 0.7301349325337332,
        "ecarts": [
            -0.02922077922077926,
            -0.022727272727272707,
            0.021361152508693526,
            -0.06344869459623559
        ],
        "ecart": 0.03418947476324527
    },
    "texte": [
        [
            "ARREST",
            "DE LA COVR",
            "DE PARLEMFNT",
            "DE BOVRDEAVX.",
            "Portant enjonction à tous les Marchands du haut-pays, de fai",
            "re deſcendre par la Garonne, des bleds, ſur le Port & Haure",
            "de la preſente Ville, pour ſubuenir à la neceßité de Paris.",
            "Ixoute la copie imprimée à Bourdeaux.",
            "A PARIS,",
            "Chez GVUILLAVME SASSIER, Imprimeur & Libraire",
            "ordinaire du Roy, rüe des Cordiers, proche",
            "Sorbonne, aux deurs Touterelles.",
            "M. DC. XXXXIX."
        ],
        [
            "EXTRAICT",
            "DES",
            "REGISTRES",
            "DV",
            "PARLEMENT.",
            "SVR ce qui a eſté repreſen",
            "té à la cour, qu’elle a don",
            "né julques icy diuers Ar",
            "ûé reſts, four la liberté de la",
            "deſcente des bleds & tranſ",
            "port d’iceux, ſuiuant les paſſe-ports accor",
            "dezpar le Roy, ſans que juſques à̀ preſent",
            "ceux qui ont entrepris la ruyne de cette",
            "A ij"
        ],
        [
            "’prouinee y ayent volu defferer, ny fai",
            "re ceſſer les empeſchemens qu’ls ont ſ",
            "porté à ce Commerce, quoy qu’il ne s’a",
            "giſt pas tant de l’intereſt de la preſente",
            "ville, où ptr la grace de Dieu, le bled",
            "n’a jamais augmenté de prix pendant ces",
            "guerres, que de celuy du haut-pays, &",
            "autres lieux de la Guyenne, qui ſe trou",
            "uans ſurchargez de bleds, pourroient re",
            "tirer de norables ſommes de la vente de",
            "cette denrée, & pouruoir pr ce moyen",
            "à leur ſubſiſtance, & au payement des de",
            "niers Royaux. Ceux meſme qui empeſ",
            "chent à preſent cette liberté, lors que le",
            "Roy la donne, ayant voulu prendre cy",
            "deuant occaſion de ſoûleuer le meſme",
            "pays de haut, contre l’autlorité de Ia",
            "Cour, pource qu’elle empeſchoit la cat",
            "gaiſon des bleds, en vn temps auquel ſa",
            "Majeſteé́ l’auoit deſfenduë, & noſtre pro",
            "pre neceſſité ne la pouuoit fouffriur: Ils",
            "vuloient en retirer des gains & profits",
            "illicites & honteux. Et d’autant qu’outre",
            "cet intereſt de coute la Prouince, la pluſ",
            "pare de celles du oraume ouuen",
            "at preſentengagées, part la cherté & diſet"
        ],
        [
            "te qu’elles ſouffrent, & particuliererment la",
            "ville de Paris, pour le ſoulagement de",
            "laquelle principalement, ces paſſe-ports",
            "auoient eſté accordez, en ſorte que les",
            "Deputez de la Cour, qui ſont prez de leurs",
            "Majeſtez, y ont ſouffert diuers reproches",
            "de la rerention des bleds deſtinez pour",
            "Paris, & de ’empeſchement qu’on por",
            "toit de deça, à l’execution des meſmes",
            "paſſe-ports, au grand prejudice de cette vil",
            "le Capitale du Royaume, à quoy eſtant im",
            "portant de pouruoir, LACOVR, Oüy",
            "ſur ce le Procureur General du Roy, con",
            "formement aux Arreſts precedens; En",
            "joint à tous les Marchands du haut-pays,",
            "& autres trafiquants en bleds, d’en faire",
            "deſcendre inconinent & ſans delay, par",
            "la riuiene de Gronne & autres, ſur le",
            "Port & Haure de la preſente ville, pour",
            "en eſtre fait eatgaiſon, ſuiuant la volonté",
            "du Roy, & eſtre pourneu par ce moyen",
            "à la neceſſité́ preſente de la ville de Pa",
            "ris, & autres hieux du Royaume. Enjoint",
            "à tou les Iuges, Maires & Conſuls, & au",
            "tres Officiers des villes, eſemble à tous",
            "Gouuerneurs des Places & Chefs des trou"
        ],
        [
            "ſages pour cet éffet, à̀ peine d’en reſpon",
            "dre en leur propre & priué nom. Fait",
            "tres-expreſſes inhibitions & deffences à",
            "toures perſonnes, der quelque qualité &!",
            "condijtion qu’ils ſoient, d’y porter aucun",
            "obſtacle ou empeſchenent, aà̀ peine d’e",
            "ſtre procedé çontr’eux comme perturba.",
            "teurs, du repps public; & en cas de con",
            "trauentiat, rdonne qu’il leur ſera cou",
            "u ſus, & aà ces fins permet aux Officiers",
            "d’aſſembler les Communautez. Et aux fins",
            "que la choſe ſoit notoire à tous, Ordon",
            "ne que le preſent Arreſt ſera leu & publié.",
            "eés villes du haut pays, & autres lieux du.",
            "reſſort que beſoin ſera, aà cry publie, &",
            "ſon de trompe es jours de Marcheé́, & af",
            "fiçhé és lieux accouſtumez, le tout en!",
            "vertu du ſimple Dictum, attendu la matie",
            "re dont s’agiſt. Fait à BOVRDE AVX,",
            "en, ’arlement, extraordinairement aſſem",
            "blé, le quinzieſme d’Octobre, mil ſix cens",
            "quarante-neuf.",
            "Signe, DE PONTAC."
        ]
    ]
}