{
    "entête": {
        "form": "prose",
        "genre": "justification",
        "handwritten_note": false,
        "table_of_content": false,
        "illustration": false,
        "creation": "1651-02-28",
        "change": {
            "@status": "corrected",
            "@when": "2022-10-25",
            "@who": "AB"
        },
        "titre": "Justification de l'assemblée de la noblesse de France\n          tenue à Paris aux Cordeliers, l'an 1651.",
        "dates": {
            "@type": "file_creation",
            "@when": "2022-10-25",
            "#text": "25 octobre 2022"
        },
        "langue": "fra",
        "fichier": "Moreau1793_GBOOKS.xml",
        "path": "Corpus\\Mazarinades\\1701-1800\\Moreau1793_GBOOKS.xml",
        "json_path": "Corpus\\Mazarinades_jsons\\1701-1800\\Moreau1793_GBOOKS.json",
        "langue_detectee": "LGERM",
        "lexicalites": [
            0.6111111111111112,
            0.6972972972972973,
            0.5755395683453237,
            0.753125,
            0.74375,
            0.7441860465116279
        ],
        "lexicalite": 0.6919720767888308,
        "ecarts": [
            0.08618618618618612,
            -0.12175772895197357,
            0.17758543165467633,
            -0.009375000000000022,
            0.00043604651162787444
        ],
        "ecart": 0.07906807866089278
    },
    "texte": [
        [
            "VSTIFICATION",
            "E LA NOBLESSE",
            "DE FRANCE",
            "enuë à Paris aux Cordeliers, L’an 15r.",
            "APAR1S",
            "u ne 11"
        ],
        [
            "A4",
            "eteeeeeleéeeee’et?",
            "T e T ’rlr r",
            "IFICATION",
            "V I",
            "1",
            "4",
            "L’ASSEMBLEE",
            "51",
            "a",
            "T",
            "ELANOBLESSE",
            "DE FPRANCE,",
            "auë à Paris aux Cordeliers. Lan 165i.,",
            "ON ne peut dire conitre l’Aſeimlée de la",
            "Nobleſſe aucune choſe, ſinon qu’elle n’eſt pas",
            "faicte par la permiſſion du Roy, les Ordornan",
            "ffendans toutes les-Aſembleées ſans permiſfidrl",
            "ajeſté: Car les choſes dont la Nobleſſeſe plaint",
            "lles-ont elles peut parler) ſone limltées à ce qui",
            "té dans le’Odonnances des Rois, & arreſtez des:",
            "Geénéraux, leſquels ne peuuent eſtre dé́niez a",
            "ice.",
            "vraiy qu’il ya des Ordonnanices des Rois qui fohe",
            "feneës :mais il faut entendre ſous le nom de Roy",
            "ui ont ſa puiſſance & ſon auehorité́ Et pour",
            "r cela; Il eſt certain que dans les Provinces les",
            "rneurs qui ont l’authorlté du Roy- peuuent don",
            "miſionde ’aſſembler, & les Aſſemblees qui ſe",
            "r leurs ordresſont juſtes & leégitihes.",
            "la mimoelté de Roy ſon autfiorité eſt entre les",
            "le la Regeatce & du Lleutenaae Géneéral de",
            "; Il’faux done auor l’ordre d’eux pour s’aſſem",
            "A ij",
            "3"
        ],
        [
            "bMer valablement, & la Ieule queſtiom qui ſe preſente",
            "eſt de ſcavoſr &’il falſoit prendre la permiſſion de la Ré:",
            "gente cetsqecaon ,u ſuy ſuffit de l’auoir d-jeue",
            "T2",
            "tenantgenralAde Eſtat.",
            "Frtiee ? d Nobiſe et ſeaite pour ro",
            "raiſons.",
            "1. or la fferts des tinces pſoniers.",
            "l D Pot’eſpignemnt u Cardnal Mazaru.",
            "I Pu ’retabſſénent deés drots de-d NMo.",
            "bleſſe anéantis par le muaaigouvemqent de l’Eſtat.",
            "Perſonne ne peut douter que les deux premiers points",
            "n’aillenr contre la Reégente, puiſqu’il s’agiſt de la liber",
            "t́ des Prinoes, qu’elles aaoi fait eraprifonne par-le",
            "mauuais Conſeil de ſon prémier Miniſtre. Et d’éloi",
            "gner des Confſeils du Roy & de-la Erance ce preng5",
            "8",
            "Miniſtre...",
            "Il eſtort impoſſible pout ces raiſons de demander à a",
            "Régente ne peraiſſon d’aſſemblej la Nobleſſe qui",
            "auloi aue4 juſticeagircpatre ſesſetjmens. Il eſtoit",
            "neçeſſaire de s’aſſemlas comne il aeſte jagé meſme",
            "parle Parlement, Cet pourquoy ne pouuian s’adreſ",
            "ſer à la Régente, l’on’oſt adreſſé ra Lienenu ge",
            "ral de l’Eſtar & Couronne: Et ainſi l’on ne peut as dire",
            "quel ’aſſemblée de-,la Nobleſſe ſeſoit faute, que pat",
            "né ceſſit́é́ auoc pemiſſion de eluy qui a l’authorité du",
            "Roy, & qui luy ſeul luy pouuoi hbailler:- E cette occ",
            "ſion il falſoit doanc, ou ne fſe pointaſsembler, on le faire",
            "par l’ordre du-Laietenant général de l’Eſtar.",
            "Ceutqui blaſnen eete afserubleeſent de mauui",
            "ſe foy, ils l’abament on leurs anes des ſuiceipour leiſ",
            "nreleilene ae ſenene eoune le e lenu lelſenuer",
            "mis des Prmees quſentiſe découvrir, & ſeus ce moſ",
            "de forme çacht celuy qui eſt cõ̃traire à̀ leurs ſertimens",
            "comonpn"
        ],
        [
            "eorrompus, tant qu’il s’eſt agy de la ſortie des. Princes,.",
            "& de l’eloignement du Mazarin, on n’a ozé parler con",
            "tre l’Aſsemblée, & ce pendant elle n’auoit que la meſ",
            "me forme qu’elle a à preſent, & mainrenant qu’il ne s’a",
            "git que des droicts de la Nobleſse l’on chicane ſur la",
            "forme.",
            "L’vſage & la couſtume de France donne des tureurs",
            "aux mineurs qui ſont d’ordinaire leurs plus proches pa",
            "rens, afin d’auoir ſoin de leurs affaires; & d’autant qu’il",
            "ſe peut preſenter des rencoutres ou des mineurs onte",
            "quelques affaires contre leſdits tuteurs, la Loy leur bail",
            "le des ſubrogez tuteurs, leſquels en ce cas ont pouuoir",
            "d’agir poures mineurs contre leurs tuteurs, & ne reç̧oi",
            "uent aucun ordre deſdits tuteurs.",
            "Il s’agiſsoit de deux actions importantes & neéceſsai,",
            "res pour le bien de l’Eſtar, & qui eſtoient contre la Ré́,",
            "gente: il falloit donc de neceſſité, ou ne point faire le",
            "dires actions ſi neéceſsaires au bien de l’Eſtat, ou s’adre.",
            "ſer au Lieutenant général de l’Eſtat qui eſt celuy qui a le",
            "plus de puiſsances apreés la Régente.",
            "Le Parlement de Paris lors qu’il a voulu donner ſes",
            "Arreſts ſi néceſsaires & ſi vriles au bien de l’Eſtat pour",
            "l’innocence des Princes priſonaiers l’eéloſgnement du",
            "Cardinal Maarin, a deſireé eſtré appuyeé de la N obleſse",
            "& qu’elle s’aſsemblaſt: Peut-il dire apres que cette Aſ",
            "ſemiblée n’eſtpas legitime, quand meſme il y auroit quel",
            "que choſe en la forme, ce qui n’eſt pas.",
            "Le Parlement qui eſt Iuge Souuérain n’eſt point obli.",
            "gé de juger ſelon les termes prefix de la Loy, mais ſon",
            "jugement Souverain luy permet d’interpreter les termes",
            "dela Loy, & de juger ſelon leéquité ce qu’il eſtime bon,",
            "& qui l’eſt,",
            "ll o’y arien de ſi eéquitable & de meilleur que les trois",
            "ſujets pour leſquels Aſsemblée de la Nobleſse s’etfaj",
            "B"
        ],
        [
            "8",
            "te, pour retirer des Prinees du Sang priſonniers’injuſte.",
            "ment au Havre de Grace, qui eſt vn port de mer, entre",
            "les mains & au pouuoir d’vni Eſtranger leur ennemy, qui",
            "non ſeulement les pouuoit à rous momens faire périr,",
            "mais les ſortir hors de France & les mettre entre les",
            "mains des ennemls du Royaume. D’éloigner des affai",
            "res de la France vn Eſtranger qui par ruſes & artifices",
            "en auoit empieté le gouvernement & la diſpoſition en",
            "tiere, & par ſon inſuffiſance & incapacité́ la réduitteau",
            "dernier deſordre. Et pour demander auec ſouſmiſſion &",
            "reſpet la rteue des Eſtats generaux jugez néceſſaires",
            "par le Conſeil du Roy & conuquez des il y a plus de",
            "deux ans.",
            "Quand les Roſs ont conuoqueé les Eſtats générauxili",
            "les ont toûjours tenus d’autant que c’eſt vn remede vni",
            "uerſel( lequel promis à leurs ſujerts ) ne leur peut-ſtre",
            "dénie auec juſtice: La tenudë en peut-eſtre rerarde",
            "our quelque temps ſeulement & pour de grandes cau!",
            "ſes & occaſions lmportantes, qui hors cette-fois n’ot",
            "iamais paſſe vne année, peut-bn maintenant trouue",
            "étrange qu’apreés deux ans de retardement l’on en de",
            "mande la tenue.",
            "La Reine Reégcnte a ſi bien reconnu que cette aſſent",
            "blée eſtoit leégitime, qu’elle luy a accordé la tenuë dés",
            "Eſluae gseeraoue qu’ele denanioits & J a cnue",
            "Maréchal de- France, lequel a pris ſeancc dans ladite",
            "ſenhĺe, & ſine duns le euſre det lenioenou",
            "’de ladite Aſemblée ce qu’l y eſt venu dire de la partdu",
            "Roy & de Reyne, Aprés rouites ces choſes peut- on dire",
            "que cette Aſſaniblée ne ſoit pas le gitime, & ſi l’on le di",
            "h’eſt ce pas auec deſſein de faire naiſtre de nouueaus",
            "ſujets de brôillerie pour ſe vanger de ce que l’on a ſory",
            "es Princes de pjiſon & éloigné́ le Cardinal Maarin",
            "’qui eſtoínut lescauſes de tous nos maux ihteſtins) pou"
        ],
        [
            "enmpeſcher que l’on ne trauaille ſolidement à l’éclairci",
            "fſenent des deſordres de l’Eſtat, & aà la Paix générale,",
            "&luiſſer quelque imagination friuole aux perſonnes",
            "groſieéres & mal intentionné́es que le Cardinal Maza",
            "rin n’eſtoit pas cauſe de tous ſes deſordres."
        ]
    ]
}